gpuparallel/__init__.py
gpuparallel/batch.py
gpuparallel/gpuparallel.py
gpuparallel/utils.py
gpuparallel/version.py
gpuparallel-0.2.2.dist-info/LICENSE
gpuparallel-0.2.2.dist-info/METADATA
gpuparallel-0.2.2.dist-info/WHEEL
gpuparallel-0.2.2.dist-info/top_level.txt
gpuparallel-0.2.2.dist-info/RECORD
