Metadata-Version: 2.1
Name: gpuparallel
Version: 0.2.2
Summary: Joblib-like interface for parallel GPU computations (e.g. data preprocessing)
Home-page: https://gpuparallel.readthedocs.io/en/latest/?badge=latest
Author: Vladimir Ivashkin
Author-email: illusionww@gmail.com
License: MIT
License-File: LICENSE
